{
	"id": "AISWA5LDd8wMcd7",
	"json": "{\"id\":\"AISWA5LDd8wMcd7\",\"url\":\"https://happy.bg/blog/58/%D1%81%D1%83%D0%BF%D0%B5%D1%80-%D0%BE%D1%84%D0%B5%D1%80%D1%82%D0%B8-%D0%B2-happy-%D0%BB%D0%BE%D0%B7%D0%B5%D0%BD%D0%B5%D1%86\",\"loadedUrl\":\"https://happy.bg/blog/58/%D1%81%D1%83%D0%BF%D0%B5%D1%80-%D0%BE%D1%84%D0%B5%D1%80%D1%82%D0%B8-%D0%B2-happy-%D0%BB%D0%BE%D0%B7%D0%B5%D0%BD%D0%B5%D1%86\",\"uniqueKey\":\"https://happy.bg/blog/58/%D1%81%D1%83%D0%BF%D0%B5%D1%80-%D0%BE%D1%84%D0%B5%D1%80%D1%82%D0%B8-%D0%B2-happy-%D0%BB%D0%BE%D0%B7%D0%B5%D0%BD%D0%B5%D1%86\",\"method\":\"GET\",\"noRetry\":false,\"retryCount\":0,\"errorMessages\":[],\"headers\":{},\"userData\":{\"__crawlee\":{\"crawlDepth\":10,\"enqueueStrategy\":\"same-hostname\",\"state\":4}},\"handledAt\":\"2025-11-13T15:53:06.770Z\"}",
	"method": "GET",
	"orderNo": null,
	"retryCount": 0,
	"uniqueKey": "https://happy.bg/blog/58/%D1%81%D1%83%D0%BF%D0%B5%D1%80-%D0%BE%D1%84%D0%B5%D1%80%D1%82%D0%B8-%D0%B2-happy-%D0%BB%D0%BE%D0%B7%D0%B5%D0%BD%D0%B5%D1%86",
	"url": "https://happy.bg/blog/58/%D1%81%D1%83%D0%BF%D0%B5%D1%80-%D0%BE%D1%84%D0%B5%D1%80%D1%82%D0%B8-%D0%B2-happy-%D0%BB%D0%BE%D0%B7%D0%B5%D0%BD%D0%B5%D1%86"
}